LICENSE
MANIFEST.in
README.rst
milestone.py
setup.cfg
setup.py
milestone.egg-info/PKG-INFO
milestone.egg-info/SOURCES.txt
milestone.egg-info/dependency_links.txt
milestone.egg-info/requires.txt
milestone.egg-info/top_level.txt