Metadata-Version: 1.1
Name: milestone
Version: 0.2
Summary: Split an XML document by milestone element.
Home-page: https://github.com/zeth/milestone
Author: Zeth
Author-email: theology@gmail.com
License: BSD
Platform: UNKNOWN
Classifier: Programming Language :: Python :: 3
Classifier: Intended Audience :: Developers
Classifier: License :: OSI Approved :: BSD License
Classifier: Topic :: Software Development :: Libraries
Classifier: Topic :: Utilities
Classifier: Operating System :: POSIX :: Linux
Classifier: Operating System :: Microsoft :: Windows
Classifier: Operating System :: MacOS :: MacOS X
